{
  "project_info": {
    "project_number": "619235587160",
    "project_id": "cartify-cf973",
    "storage_bucket": "cartify-cf973.firebasestorage.app"
  },
  "client": [
    {
      "client_info": {
        "mobilesdk_app_id": "1:619235587160:android:3f0c07fcb1902bdaf9462d",
        "android_client_info": {
          "package_name": "com.example.cartify"
        }
      },
      "oauth_client": [],
      "api_key": [
        {
          "current_key": "AIzaSyCSzRk-hsRuJFymI_hReILtTPyOROS1R04"
        }
      ],
      "services": {
        "appinvite_service": {
          "other_platform_oauth_client": []
        }
      }
    }
  ],
  "configuration_version": "1"
}